{
    "results": [
      {
        "gender": "male",
        "name": {
          "title": "Mr",
          "first": "Viljami",
          "last": "Kauppila"
        },
        "location": {
          "street": {
            "number": 6775,
            "name": "Tahmelantie"
          },
          "city": "Sottunga",
          "state": "South Karelia",
          "country": "Finland",
          "postcode": 48519,
          "coordinates": {
            "latitude": "-26.5822",
            "longitude": "-6.4656"
          },
          "timezone": {
            "offset": "+5:00",
            "description": "Ekaterinburg, Islamabad, Karachi, Tashkent"
          }
        },
        "email": "viljami.kauppila@example.com",
        "login": {
          "uuid": "f4aaddb6-c93d-4776-ac06-1957b5488ca0",
          "username": "angrykoala192",
          "password": "sasha1",
          "salt": "XKp2DCzk",
          "md5": "72ae3df0688db9c9e69ff6996b475add",
          "sha1": "addc26c73e77aca42f84ffc0fdfb8b6991b3da06",
          "sha256": "ebd6e8ba8975d9ee94193edccbac27cdeca0d70014a5ba755f7627da0ca3392a"
        },
        "dob": {
          "date": "1979-06-18T18:03:18.460Z",
          "age": 43
        },
        "registered": {
          "date": "2008-08-06T02:17:35.762Z",
          "age": 14
        },
        "phone": "07-335-576",
        "cell": "040-016-18-81",
        "id": {
          "name": "HETU",
          "value": "NaNNA925undefined"
        },
        "picture": {
          "large": "https://randomuser.me/api/portraits/men/46.jpg",
          "medium": "https://randomuser.me/api/portraits/med/men/46.jpg",
          "thumbnail": "https://randomuser.me/api/portraits/thumb/men/46.jpg"
        },
        "nat": "FI"
      }
    ],
    "info": {
      "seed": "273f269cbc02fabd",
      "results": 1,
      "page": 1,
      "version": "1.4"
    }
  }